sequel/__init__.py
sequel/__main__.py
sequel/algo.py
sequel/cli.py
sequel/codex.py
sequel/compat.py
sequel/dag.py
sequel/io.py
sequel/ledger.py
sequel/ext/__init__.py
sequel/ext/gcp.py
sequel-0.4.2.dist-info/AUTHORS.rst
sequel-0.4.2.dist-info/LICENSE
sequel-0.4.2.dist-info/METADATA
sequel-0.4.2.dist-info/WHEEL
sequel-0.4.2.dist-info/entry_points.txt
sequel-0.4.2.dist-info/top_level.txt
sequel-0.4.2.dist-info/RECORD
