Metadata-Version: 2.1
Name: sequel
Version: 0.4.2
Summary: Opinionated imperative Everything as Code orchestrator.
Home-page: https://gitlab.com/cblegare/sequel
Author: Charles Bouchard-Légaré
Author-email: cblegare.atl@ntis.ca
License: GNU Lesser General Public License v3
Download-URL: https://gitlab.com/cblegare/sequel/repository/master/archive.tar.gz
Project-URL: Bug Tracker, https://gitlab.com/cblegare/sequel/issues
Project-URL: Documentation, https://cblegare.gitlab.io/sequel
Project-URL: Source Code, https://gitlab.com/cblegare/sequel
Platform: UNKNOWN
Classifier: Programming Language :: Python
Classifier: Programming Language :: Python :: 3.5
Classifier: Programming Language :: Python :: 3.6
Classifier: Programming Language :: Python :: 3.7
Classifier: Programming Language :: Python :: Implementation :: CPython
Classifier: Development Status :: 2 - Pre-Alpha
Classifier: Environment :: Console
Classifier: Operating System :: OS Independent
Classifier: Intended Audience :: Developers
Classifier: Intended Audience :: System Administrators
Classifier: License :: OSI Approved :: GNU General Public License v3 or later (GPLv3+)
Requires-Dist: click
Requires-Dist: arrow
Provides-Extra: all
Requires-Dist: setuptools (>=30.3) ; extra == 'all'
Requires-Dist: wheel ; extra == 'all'
Requires-Dist: google-cloud-storage ; extra == 'all'
Requires-Dist: sphinx ; extra == 'all'
Requires-Dist: sphinx-rtd-theme ; extra == 'all'
Requires-Dist: sphinx-click ; extra == 'all'
Requires-Dist: sphinx-paramlinks ; extra == 'all'
Requires-Dist: tox ; extra == 'all'
Requires-Dist: jsonschema ; extra == 'all'
Requires-Dist: testfixtures ; extra == 'all'
Requires-Dist: pytest ; extra == 'all'
Requires-Dist: pytest-cov ; extra == 'all'
Requires-Dist: flake8 ; extra == 'all'
Requires-Dist: flake8-codeclimate ; extra == 'all'
Requires-Dist: twine ; extra == 'all'
Requires-Dist: bandit ; extra == 'all'
Provides-Extra: build_system
Requires-Dist: setuptools (>=30.3) ; extra == 'build_system'
Requires-Dist: wheel ; extra == 'build_system'
Provides-Extra: documenting
Requires-Dist: sphinx ; extra == 'documenting'
Requires-Dist: sphinx-rtd-theme ; extra == 'documenting'
Requires-Dist: sphinx-click ; extra == 'documenting'
Requires-Dist: sphinx-paramlinks ; extra == 'documenting'
Requires-Dist: google-cloud-storage ; extra == 'documenting'
Provides-Extra: google_cloud
Requires-Dist: google-cloud-storage ; extra == 'google_cloud'
Provides-Extra: lint
Requires-Dist: flake8 ; extra == 'lint'
Requires-Dist: flake8-codeclimate ; extra == 'lint'
Provides-Extra: releaseing
Requires-Dist: twine ; extra == 'releaseing'
Provides-Extra: sec
Requires-Dist: bandit ; extra == 'sec'
Provides-Extra: testing
Requires-Dist: tox ; extra == 'testing'
Requires-Dist: jsonschema ; extra == 'testing'
Requires-Dist: testfixtures ; extra == 'testing'
Requires-Dist: pytest ; extra == 'testing'
Requires-Dist: pytest-cov ; extra == 'testing'
Requires-Dist: google-cloud-storage ; extra == 'testing'
